EZPaginator/EZPaginator.py
EZPaginator/__init__.py
EZPaginator/exceptions.py
EZPaginator-2.0.0.dist-info/LICENSE
EZPaginator-2.0.0.dist-info/METADATA
EZPaginator-2.0.0.dist-info/WHEEL
EZPaginator-2.0.0.dist-info/top_level.txt
EZPaginator-2.0.0.dist-info/RECORD
