Metadata-Version: 2.1
Name: EZPaginator
Version: 2.0.0
Summary: Python library for discord.py pagination.
Home-page: https://github.com/khk4912/EZPaginator
Author: khk4912
Author-email: khk49121@gmail.com
License: MIT
Keywords: discord.py,pagination
Classifier: Programming Language :: Python :: 3
Classifier: Programming Language :: Python :: 3.9
Classifier: Programming Language :: Python :: 3.10
Requires-Python: >=3.9
License-File: LICENSE
Requires-Dist: discord.py
